{"cameraMode":{"drawMode":0,"name":"Shaded","section":"Shading Mode"},"sceneLighting":true,"audioPlay":false,"sceneViewState":{"m_AlwaysRefresh":false,"showFog":true,"showSkybox":true,"showFlares":true,"showImageEffects":true,"showParticleSystems":true,"showVisualEffectGraphs":true,"m_FxEnabled":true},"in2DMode":false,"pivot":{"x":2.4182655811309816,"y":4.29777717590332,"z":-1.668408989906311},"rotation":{"x":-0.10802879929542542,"y":0.6699005365371704,"z":-0.09936972707509995,"w":-0.7278305888175964},"size":0.4140198826789856,"orthographic":false}